pyAliceKit/__init__.py
pyAliceKit/base.py
pyAliceKit/pya.py
pyAliceKit/GUI/localserver.py
pyAliceKit/GUI/utils/html.py
pyAliceKit/GUI/views/get/get_dialog_nodes.py
pyAliceKit/GUI/views/get/get_settings_const.py
pyAliceKit/GUI/views/get/settings.py
pyAliceKit/GUI/views/post/settings_change_simple.py
pyAliceKit/core/__init__.py
pyAliceKit/core/buttons.py
pyAliceKit/core/dialog_engine.py
pyAliceKit/core/event_emitter.py
pyAliceKit/core/intents.py
pyAliceKit/core/key_words.py
pyAliceKit/core/session_storage.py
pyAliceKit/messages/embedded_errors_message.py
pyAliceKit/messages/embedded_message.py
pyAliceKit/py_alice/py_alice.py
pyAliceKit/py_alice/processors/came_message.py
pyAliceKit/py_alice/processors/keyword_and_intents.py
pyAliceKit/py_alice/processors/new.py
pyAliceKit/py_alice/processors/response_for_alice.py
pyAliceKit/py_alice/processors/service_storage.py
pyAliceKit/py_alice/processors/storage.py
pyAliceKit/utils/__init__.py
pyAliceKit/utils/dialogs.py
pyAliceKit/utils/dialogs_validation.py
pyAliceKit/utils/settings_validation.py
pyAliceKit/utils/terminal.py
pyAliceKit/utils/tools.py
pyAliceKit/utils/errors/errors.py
pyalicekit-0.1.0.dist-info/licenses/LICENSE
pyalicekit-0.1.0.dist-info/METADATA
pyalicekit-0.1.0.dist-info/WHEEL
pyalicekit-0.1.0.dist-info/top_level.txt
pyalicekit-0.1.0.dist-info/RECORD
