Metadata-Version: 2.4
Name: pyAliceKit
Version: 0.1.0
Summary: pyAliceKit framework for creating dialog bots on Yandex.Alice
Author-email: SergeyOborok2005 <sergejoborok00@gmail.com>
License-Expression: MIT
Project-URL: Homepage, https://sergey200519.github.io/pyAlice-documentation/
Project-URL: Source, https://github.com/Sergey200519/pyAliceKit
Project-URL: Documentation, https://sergey200519.github.io/portfolio/pyAliceKit-docs
Classifier: Programming Language :: Python :: 3
Classifier: Operating System :: OS Independent
Requires-Python: >=3.10
License-File: LICENSE
Requires-Dist: Flask<3.0,>=2.3
Requires-Dist: typing-extensions<5.0,>=4.7
Dynamic: license-file
